EZannot/__init__.py
EZannot/__main__.py
EZannot/annotator.py
EZannot/annotators/__init__.py
EZannot/detectron2/__init__.py
EZannot/detectron2/checkpoint/__init__.py
EZannot/detectron2/checkpoint/c2_model_loading.py
EZannot/detectron2/checkpoint/catalog.py
EZannot/detectron2/checkpoint/detection_checkpoint.py
EZannot/detectron2/config/__init__.py
EZannot/detectron2/config/compat.py
EZannot/detectron2/config/config.py
EZannot/detectron2/config/defaults.py
EZannot/detectron2/config/instantiate.py
EZannot/detectron2/config/lazy.py
EZannot/detectron2/data/__init__.py
EZannot/detectron2/data/benchmark.py
EZannot/detectron2/data/build.py
EZannot/detectron2/data/catalog.py
EZannot/detectron2/data/common.py
EZannot/detectron2/data/dataset_mapper.py
EZannot/detectron2/data/datasets/__init__.py
EZannot/detectron2/data/datasets/builtin.py
EZannot/detectron2/data/datasets/builtin_meta.py
EZannot/detectron2/data/datasets/cityscapes.py
EZannot/detectron2/data/datasets/cityscapes_panoptic.py
EZannot/detectron2/data/datasets/coco.py
EZannot/detectron2/data/datasets/coco_panoptic.py
EZannot/detectron2/data/datasets/lvis.py
EZannot/detectron2/data/datasets/lvis_v0_5_categories.py
EZannot/detectron2/data/datasets/lvis_v1_categories.py
EZannot/detectron2/data/datasets/lvis_v1_category_image_count.py
EZannot/detectron2/data/datasets/pascal_voc.py
EZannot/detectron2/data/datasets/register_coco.py
EZannot/detectron2/data/detection_utils.py
EZannot/detectron2/data/samplers/__init__.py
EZannot/detectron2/data/samplers/distributed_sampler.py
EZannot/detectron2/data/samplers/grouped_batch_sampler.py
EZannot/detectron2/data/transforms/__init__.py
EZannot/detectron2/data/transforms/augmentation.py
EZannot/detectron2/data/transforms/augmentation_impl.py
EZannot/detectron2/data/transforms/transform.py
EZannot/detectron2/engine/__init__.py
EZannot/detectron2/engine/defaults.py
EZannot/detectron2/engine/hooks.py
EZannot/detectron2/engine/launch.py
EZannot/detectron2/engine/train_loop.py
ezannot-0.9.8.dist-info/METADATA
ezannot-0.9.8.dist-info/WHEEL
ezannot-0.9.8.dist-info/entry_points.txt
ezannot-0.9.8.dist-info/licenses/LICENSE
ezannot-0.9.8.dist-info/licenses/NOTICE.txt
ezannot-0.9.8.dist-info/RECORD
