Metadata-Version: 2.1
Name: EZannot
Version: 0.9.8
Summary: Annotate images and measure the annotated with ease.
Keywords: Image annotation,Quantification of annotated objects,AI-assisted annotation,Image augmentation
Author-Email: Yujia Hu <yujiahu415@gmail.com>
License: GPL-3.0
Classifier: License :: OSI Approved :: GNU General Public License v3 (GPLv3)
Classifier: Operating System :: OS Independent
Classifier: Programming Language :: Python :: 3
Classifier: Programming Language :: Python :: 3 :: Only
Classifier: Programming Language :: Python :: 3.10
Classifier: Programming Language :: Python :: 3.11
Classifier: Programming Language :: Python :: 3.12
Classifier: Programming Language :: Python :: 3.13
Project-URL: Homepage, https://github.com/yujiahu415/EZannot
Requires-Python: >=3.10
Requires-Dist: numpy>=1.24.4
Requires-Dist: scipy
Requires-Dist: scikit-image
Requires-Dist: opencv-python
Requires-Dist: opencv-contrib-python
Requires-Dist: pillow>=9.4.0
Requires-Dist: wxPython
Requires-Dist: packaging
Requires-Dist: requests
Requires-Dist: screeninfo
Requires-Dist: openpyxl
Requires-Dist: pandas
Requires-Dist: tifffile
Requires-Dist: imagecodecs
Requires-Dist: tqdm>=4.66.1
Requires-Dist: hydra-core>=1.3.2
Requires-Dist: iopath>=0.1.10
Requires-Dist: torch>=2.5.1
Requires-Dist: torchvision>=0.20.1
Requires-Dist: torchaudio
Requires-Dist: matplotlib
Requires-Dist: pycocotools>=2.0.2
Requires-Dist: termcolor>=1.1
Requires-Dist: yacs>=0.1.8
Requires-Dist: tabulate
Requires-Dist: cloudpickle
Requires-Dist: tensorboard
Requires-Dist: fvcore<0.1.6,>=0.1.5
Requires-Dist: iopath>=0.1.7
Requires-Dist: dataclasses; python_version < "3.7"
Requires-Dist: omegaconf<2.4,>=2.1
Requires-Dist: black
Requires-Dist: ninja
Requires-Dist: six
